{
    "Turner": {
        "1": "https://quizstcapi.herokuapp.com/turner/1",
        "2": "https://quizstcapi.herokuapp.com/turner/2",
        "3": "https://quizstcapi.herokuapp.com/turner/3",
        "4": "https://quizstcapi.herokuapp.com/turner/4",
        "5": "https://quizstcapi.herokuapp.com/turner/5",
        "6": "https://quizstcapi.herokuapp.com/turner/6",
        "7": "https://quizstcapi.herokuapp.com/turner/7",
        "8": "https://quizstcapi.herokuapp.com/turner/8",
        "9": "https://quizstcapi.herokuapp.com/turner/9",
        "10": "https://quizstcapi.herokuapp.com/turner/10",
        "11": "https://quizstcapi.herokuapp.com/turner/11",
        "12": "https://quizstcapi.herokuapp.com/turner/12",
        "13": "https://quizstcapi.herokuapp.com/turner/13",
        "14": "https://quizstcapi.herokuapp.com/turner/14",
        "15": "https://quizstcapi.herokuapp.com/turner/15",
        "16": "https://quizstcapi.herokuapp.com/turner/16",
        "17": "https://quizstcapi.herokuapp.com/turner/17",
        "18": "https://quizstcapi.herokuapp.com/turner/18",
        "19": "https://quizstcapi.herokuapp.com/turner/19",
        "20": "https://quizstcapi.herokuapp.com/turner/20",
        "21": "https://quizstcapi.herokuapp.com/turner/21",
        "22": "https://quizstcapi.herokuapp.com/turner/22",
        "23": "https://quizstcapi.herokuapp.com/turner/23",
        "24": "https://quizstcapi.herokuapp.com/turner/24",
        "25": "https://quizstcapi.herokuapp.com/turner/25",
        "26": "https://quizstcapi.herokuapp.com/turner/26",
        "27": "https://quizstcapi.herokuapp.com/turner/27",
        "28": "https://quizstcapi.herokuapp.com/turner/28",
        "29": "https://quizstcapi.herokuapp.com/turner/29",
        "30": "https://quizstcapi.herokuapp.com/turner/30",
        "31": "https://quizstcapi.herokuapp.com/turner/31",
        "32": "https://quizstcapi.herokuapp.com/turner/32",
        "33": "https://quizstcapi.herokuapp.com/turner/33",
        "34": "https://quizstcapi.herokuapp.com/turner/34",
        "35": "https://quizstcapi.herokuapp.com/turner/35",
        "36": "https://quizstcapi.herokuapp.com/turner/36",
        "37": "https://quizstcapi.herokuapp.com/turner/37",
        "38": "https://quizstcapi.herokuapp.com/turner/38",
        "39": "https://quizstcapi.herokuapp.com/turner/39"
    },
    "Fitter": {
        "1": "https://quizstcapi.herokuapp.com/fitter/1",
        "2": "https://quizstcapi.herokuapp.com/fitter/2",
        "3": "https://quizstcapi.herokuapp.com/fitter/3",
        "4": "https://quizstcapi.herokuapp.com/fitter/4",
        "5": "https://quizstcapi.herokuapp.com/fitter/5",
        "6": "https://quizstcapi.herokuapp.com/fitter/6",
        "7": "https://quizstcapi.herokuapp.com/fitter/7",
        "8": "https://quizstcapi.herokuapp.com/fitter/8",
        "9": "https://quizstcapi.herokuapp.com/fitter/9",
        "10": "https://quizstcapi.herokuapp.com/fitter/10",
        "11": "https://quizstcapi.herokuapp.com/fitter/11",
        "12": "https://quizstcapi.herokuapp.com/fitter/12",
        "13": "https://quizstcapi.herokuapp.com/fitter/13",
        "14": "https://quizstcapi.herokuapp.com/fitter/14",
        "15": "https://quizstcapi.herokuapp.com/fitter/15",
        "16": "https://quizstcapi.herokuapp.com/fitter/16",
        "17": "https://quizstcapi.herokuapp.com/fitter/17",
        "18": "https://quizstcapi.herokuapp.com/fitter/18",
        "19": "https://quizstcapi.herokuapp.com/fitter/19",
        "20": "https://quizstcapi.herokuapp.com/fitter/20",
        "21": "https://quizstcapi.herokuapp.com/fitter/21",
        "22": "https://quizstcapi.herokuapp.com/fitter/22",
        "23": "https://quizstcapi.herokuapp.com/fitter/23",
        "24": "https://quizstcapi.herokuapp.com/fitter/24",
        "25": "https://quizstcapi.herokuapp.com/fitter/25",
        "26": "https://quizstcapi.herokuapp.com/fitter/26",
        "27": "https://quizstcapi.herokuapp.com/fitter/27",
        "28": "https://quizstcapi.herokuapp.com/fitter/28",
        "29": "https://quizstcapi.herokuapp.com/fitter/29",
        "30": "https://quizstcapi.herokuapp.com/fitter/30",
        "31": "https://quizstcapi.herokuapp.com/fitter/31",
        "32": "https://quizstcapi.herokuapp.com/fitter/32",
        "33": "https://quizstcapi.herokuapp.com/fitter/33",
        "34": "https://quizstcapi.herokuapp.com/fitter/34",
        "35": "https://quizstcapi.herokuapp.com/fitter/35",
        "36": "https://quizstcapi.herokuapp.com/fitter/36",
        "37": "https://quizstcapi.herokuapp.com/fitter/37",
        "38": "https://quizstcapi.herokuapp.com/fitter/38",
        "39": "https://quizstcapi.herokuapp.com/fitter/39"

    },
    "ES": {
        "1": "https://quizstcapi.herokuapp.com/es/1",
        "2": "https://quizstcapi.herokuapp.com/es/2",
        "3": "https://quizstcapi.herokuapp.com/es/3",
        "4": "https://quizstcapi.herokuapp.com/es/4",
        "5": "https://quizstcapi.herokuapp.com/es/5",
        "6": "https://quizstcapi.herokuapp.com/es/6",
        "7": "https://quizstcapi.herokuapp.com/es/7",
        "8": "https://quizstcapi.herokuapp.com/es/8"
    },
    "Electrician": {
        "1": "https://quizstcapi.herokuapp.com/electrician/1",
        "2": "https://quizstcapi.herokuapp.com/electrician/2",
        "3": "https://quizstcapi.herokuapp.com/electrician/3",
        "4": "https://quizstcapi.herokuapp.com/electrician/4",
        "5": "https://quizstcapi.herokuapp.com/electrician/5",
        "6": "https://quizstcapi.herokuapp.com/electrician/6",
        "7": "https://quizstcapi.herokuapp.com/electrician/7",
        "8": "https://quizstcapi.herokuapp.com/electrician/8",
        "9": "https://quizstcapi.herokuapp.com/electrician/9",
        "10": "https://quizstcapi.herokuapp.com/electrician/10",
        "11": "https://quizstcapi.herokuapp.com/electrician/11",
        "12": "https://quizstcapi.herokuapp.com/electrician/12",
        "13": "https://quizstcapi.herokuapp.com/electrician/13",
        "14": "https://quizstcapi.herokuapp.com/electrician/14",
        "15": "https://quizstcapi.herokuapp.com/electrician/15",
        "16": "https://quizstcapi.herokuapp.com/electrician/16",
        "17": "https://quizstcapi.herokuapp.com/electrician/17",
        "18": "https://quizstcapi.herokuapp.com/electrician/18",
        "19": "https://quizstcapi.herokuapp.com/electrician/19",
        "20": "https://quizstcapi.herokuapp.com/electrician/20",
        "21": "https://quizstcapi.herokuapp.com/electrician/21",
        "22": "https://quizstcapi.herokuapp.com/electrician/22",
        "23": "https://quizstcapi.herokuapp.com/electrician/23",
        "24": "https://quizstcapi.herokuapp.com/electrician/24"

    },
    "COPA": {
        "1": "https://quizstcapi.herokuapp.com/copa/1",
        "2": "https://quizstcapi.herokuapp.com/copa/2",
        "3": "https://quizstcapi.herokuapp.com/copa/3",
        "4": "https://quizstcapi.herokuapp.com/copa/4",
        "5": "https://quizstcapi.herokuapp.com/copa/5",
        "6": "https://quizstcapi.herokuapp.com/copa/6",
        "7": "https://quizstcapi.herokuapp.com/copa/7",
        "8": "https://quizstcapi.herokuapp.com/copa/8",
        "9": "https://quizstcapi.herokuapp.com/copa/9",
        "10": "https://quizstcapi.herokuapp.com/copa/10",
        "11": "https://quizstcapi.herokuapp.com/copa/11",
        "12": "https://quizstcapi.herokuapp.com/copa/12",
        "13": "https://quizstcapi.herokuapp.com/copa/13",
        "14": "https://quizstcapi.herokuapp.com/copa/14",
        "15": "https://quizstcapi.herokuapp.com/copa/15",
        "16": "https://quizstcapi.herokuapp.com/copa/16",
        "17": "https://quizstcapi.herokuapp.com/copa/17",
        "18": "https://quizstcapi.herokuapp.com/copa/18",
        "19": "https://quizstcapi.herokuapp.com/copa/19",
        "20": "https://quizstcapi.herokuapp.com/copa/20",
        "21": "https://quizstcapi.herokuapp.com/copa/21"
    },
    "CNC VMC": {
        "1": "https://quizstcapi.herokuapp.com/cv/1",
        "2": "https://quizstcapi.herokuapp.com/cv/2",
        "3": "https://quizstcapi.herokuapp.com/cv/3",
        "4": "https://quizstcapi.herokuapp.com/cv/4",
        "5": "https://quizstcapi.herokuapp.com/cv/5",
        "6": "https://quizstcapi.herokuapp.com/cv/6",
        "7": "https://quizstcapi.herokuapp.com/cv/7",
        "8": "https://quizstcapi.herokuapp.com/cv/8",
        "9": "https://quizstcapi.herokuapp.com/cv/9",
        "10": "https://quizstcapi.herokuapp.com/cv/10",
        "11": "https://quizstcapi.herokuapp.com/cv/11",
        "12": "https://quizstcapi.herokuapp.com/cv/12",
        "13": "https://quizstcapi.herokuapp.com/cv/13",
        "14": "https://quizstcapi.herokuapp.com/cv/14"

    },
    "Maths Science": {
        "1": "https://quizstcapi.herokuapp.com/m_s/1",
        "2": "https://quizstcapi.herokuapp.com/m_s/2",
        "3": "https://quizstcapi.herokuapp.com/m_s/3",
        "4": "https://quizstcapi.herokuapp.com/m_s/4",
        "5": "https://quizstcapi.herokuapp.com/m_s/5",
        "6": "https://quizstcapi.herokuapp.com/m_s/6",
        "7": "https://quizstcapi.herokuapp.com/m_s/7",
        "8": "https://quizstcapi.herokuapp.com/m_s/8",
        "9": "https://quizstcapi.herokuapp.com/m_s/9",
        "10": "https://quizstcapi.herokuapp.com/m_s/10",
        "11": "https://quizstcapi.herokuapp.com/m_s/11",
        "12": "https://quizstcapi.herokuapp.com/m_s/12",
        "13": "https://quizstcapi.herokuapp.com/m_s/13",
        "14": "https://quizstcapi.herokuapp.com/m_s/14",
        "15": "https://quizstcapi.herokuapp.com/m_s/15",
        "16": "https://quizstcapi.herokuapp.com/m_s/16",
        "17": "https://quizstcapi.herokuapp.com/m_s/17",
        "18": "https://quizstcapi.herokuapp.com/m_s/18",
        "19": "https://quizstcapi.herokuapp.com/m_s/19",
        "20": "https://quizstcapi.herokuapp.com/m_s/20"

    },
    "Mechanical Disel": {
        "1": "https://quizstcapi.herokuapp.com/md/1",
        "2": "https://quizstcapi.herokuapp.com/md/2",
        "3": "https://quizstcapi.herokuapp.com/md/3",
        "4": "https://quizstcapi.herokuapp.com/md/4",
        "5": "https://quizstcapi.herokuapp.com/md/5",
        "6": "https://quizstcapi.herokuapp.com/md/6",
        "7": "https://quizstcapi.herokuapp.com/md/7",
        "8": "https://quizstcapi.herokuapp.com/md/8",
        "9": "https://quizstcapi.herokuapp.com/md/9",
        "10": "https://quizstcapi.herokuapp.com/md/10"
    },
    "MRAC": {
        "1": "https://quizstcapi.herokuapp.com/mrac/1",
        "2": "https://quizstcapi.herokuapp.com/mrac/2",
        "3": "https://quizstcapi.herokuapp.com/mrac/3",
        "4": "https://quizstcapi.herokuapp.com/mrac/4",
        "5": "https://quizstcapi.herokuapp.com/mrac/5",
        "6": "https://quizstcapi.herokuapp.com/mrac/6",
        "7": "https://quizstcapi.herokuapp.com/mrac/7",
        "8": "https://quizstcapi.herokuapp.com/mrac/8",
        "9": "https://quizstcapi.herokuapp.com/mrac/9",
        "10": "https://quizstcapi.herokuapp.com/mrac/10",
        "11": "https://quizstcapi.herokuapp.com/mrac/11",
        "12": "https://quizstcapi.herokuapp.com/mrac/12",
        "13": "https://quizstcapi.herokuapp.com/mrac/13",
        "14": "https://quizstcapi.herokuapp.com/mrac/14",
        "15": "https://quizstcapi.herokuapp.com/mrac/15",
        "16": "https://quizstcapi.herokuapp.com/mrac/16",
        "17": "https://quizstcapi.herokuapp.com/mrac/17",
        "18": "https://quizstcapi.herokuapp.com/mrac/18",
        "19": "https://quizstcapi.herokuapp.com/mrac/19",
        "20": "https://quizstcapi.herokuapp.com/mrac/20",
        "21": "https://quizstcapi.herokuapp.com/mrac/21",
        "22": "https://quizstcapi.herokuapp.com/mrac/22",
        "23": "https://quizstcapi.herokuapp.com/mrac/23",
        "24": "https://quizstcapi.herokuapp.com/mrac/24",
        "25": "https://quizstcapi.herokuapp.com/mrac/25",
        "26": "https://quizstcapi.herokuapp.com/mrac/26",
        "27": "https://quizstcapi.herokuapp.com/mrac/27",
        "28": "https://quizstcapi.herokuapp.com/mrac/28",
        "29": "https://quizstcapi.herokuapp.com/mrac/29",
        "30": "https://quizstcapi.herokuapp.com/mrac/30",
        "31": "https://quizstcapi.herokuapp.com/mrac/31",
        "32": "https://quizstcapi.herokuapp.com/mrac/32",
        "33": "https://quizstcapi.herokuapp.com/mrac/33",
        "34": "https://quizstcapi.herokuapp.com/mrac/34",
        "35": "https://quizstcapi.herokuapp.com/mrac/35",
        "36": "https://quizstcapi.herokuapp.com/mrac/36",
        "37": "https://quizstcapi.herokuapp.com/mrac/37",
        "38": "https://quizstcapi.herokuapp.com/mrac/38",
        "39": "https://quizstcapi.herokuapp.com/mrac/39"
    }
}